howto_pypi/__init__.py
howto_pypi/display.py
howto_pypi-0.0.6.dist-info/DESCRIPTION.rst
howto_pypi-0.0.6.dist-info/METADATA
howto_pypi-0.0.6.dist-info/RECORD
howto_pypi-0.0.6.dist-info/WHEEL
howto_pypi-0.0.6.dist-info/metadata.json
howto_pypi-0.0.6.dist-info/top_level.txt
