Metadata-Version: 2.0
Name: howto-pypi
Version: 0.0.6
Summary: A template project about how to package and distribute rojects
Home-page: https://github.com/yang-zhang/howto-pypi
Author: UNKNOWN
Author-email: UNKNOWN
License: UNKNOWN
Platform: UNKNOWN
